basta/__about__.py
basta/__init__.py
basta/bastamain.py
basta/constants.py
basta/distances.py
basta/downloader.py
basta/downloader_examples.py
basta/fileio.py
basta/freq_fit.py
basta/glitch_fit.py
basta/glitch_fq.f95
basta/glitch_sd.f95
basta/icov_sd.f95
basta/interpolation_across.py
basta/interpolation_along.py
basta/interpolation_combined.py
basta/interpolation_driver.py
basta/interpolation_helpers.py
basta/plot_corner.py
basta/plot_driver.py
basta/plot_interp.py
basta/plot_kiel.py
basta/plot_seismic.py
basta/plots.mplstyle
basta/priors.py
basta/process_output.py
basta/run.py
basta/sd.f95
basta/stats.py
basta/utils_distances.py
basta/utils_examples.py
basta/utils_general.py
basta/utils_seismic.py
basta/utils_xml.py
basta/xml_create.py
basta/xml_run.py
basta-1.5.3.dist-info/METADATA
basta-1.5.3.dist-info/WHEEL
basta-1.5.3.dist-info/entry_points.txt
basta-1.5.3.dist-info/licenses/LICENSE
basta-1.5.3.dist-info/RECORD
