Metadata-Version: 2.4
Name: BASTA
Version: 1.5.3
Summary: The BAyesian STellar Algorithm
Project-URL: Homepage, https://github.com/BASTAcode/BASTA
Project-URL: Documentation, https://basta.readthedocs.io
Project-URL: Issues, https://github.com/BASTAcode/BASTA/issues
Project-URL: Repository, https://github.com/BASTAcode/BASTA.git
Author-email: The BASTA Team <jakob@phys.au.dk>
Maintainer-email: Jakob Lysgaard Rørsted <jakob@phys.au.dk>
License: MIT License
License-File: LICENSE
Classifier: Development Status :: 5 - Production/Stable
Classifier: Intended Audience :: Science/Research
Classifier: License :: OSI Approved :: MIT License
Classifier: Programming Language :: Python :: 3
Classifier: Programming Language :: Python :: 3.10
Classifier: Programming Language :: Python :: 3.11
Classifier: Programming Language :: Python :: 3.12
Classifier: Topic :: Scientific/Engineering :: Astronomy
Requires-Python: >=3.10
Requires-Dist: astropy>=6.1.4
Requires-Dist: black>=24.10.0
Requires-Dist: bottleneck>=1.4.2
Requires-Dist: dustmaps>=1.0.13
Requires-Dist: h5py>=3.12.1
Requires-Dist: healpy>=1.18.0
Requires-Dist: matplotlib>=3.9.2
Requires-Dist: numpy>=2.1.3
Requires-Dist: pre-commit>=4.0.1
Requires-Dist: scikit-learn>=1.5.2
Requires-Dist: scipy>=1.14.1
Requires-Dist: tqdm>=4.67.0
